partix/PartixEvalListener.py
partix/PartixLexer.py
partix/PartixListener.py
partix/PartixParser.py
partix/__init__.py
partix/preprocessor.py
partix/run_partix.py
partix-0.1.4.dist-info/METADATA
partix-0.1.4.dist-info/WHEEL
partix-0.1.4.dist-info/top_level.txt
partix-0.1.4.dist-info/RECORD
