Metadata-Version: 2.4
Name: partix
Version: 0.1.4
Summary: A minimal test package for publishing to PyPI
Author-email: HJH <me@example.com>
License: MIT
Project-URL: Homepage, https://example.igrashiyouma.com
Requires-Dist: antlr4-python3-runtime<5,>=4.11
Requires-Dist: jsonpath_ng==1.7.0
